LICENSE.txt
MANIFEST.in
README.md
setup.cfg
setup.py
s3client/__init__.py
s3client/s3client.py
s3streamcat/__init__.py
s3streamcat/s3streamcat.py
s3streamcat.egg-info/PKG-INFO
s3streamcat.egg-info/SOURCES.txt
s3streamcat.egg-info/dependency_links.txt
s3streamcat.egg-info/entry_points.txt
s3streamcat.egg-info/not-zip-safe
s3streamcat.egg-info/requires.txt
s3streamcat.egg-info/top_level.txt