Metadata-Version: 1.1
Name: s3streamcat
Version: 0.1.6
Summary: Streaming based unix cat like functionality for file on S3. Supports gzip, bzip and xz compressed files as well
Home-page: https://github.com/samarthg/s3streamcat
Author: Samarth Gahire
Author-email: samarth.gahire@gmail.com
License: MIT
Download-URL: https://github.com/samarthg/s3streamcat/archive/v0.1.6.tar.gz
Keywords: s3cat,s3,print,aws,cat,stream,gzip,bzip,xz
Platform: UNKNOWN
